{
    "metadata": {
        "streamsync_version": "0.5.0"
    },
    "components": {
        "root": {
            "id": "root",
            "type": "root",
            "content": {
                "appName": "vinskraper"
            },
            "isCodeManaged": false,
            "position": 0,
            "handlers": {},
            "visible": true
        },
        "ccad7k7sc5oxy81l": {
            "id": "ccad7k7sc5oxy81l",
            "type": "page",
            "content": {
                "accentColor": "#F3F7F4",
                "emptinessColor": "#FFFFFF",
                "primaryTextColor": "#06070E",
                "secondaryTextColor": "#136F63",
                "containerBackgroundColor": "#F3F7F4",
                "separatorColor": "#06070E",
                "selectedColor": "#136F63",
                "cssClasses": "",
                "buttonColor": "#F3F7F4",
                "buttonTextColor": "#136F63"
            },
            "isCodeManaged": false,
            "position": 0,
            "parentId": "root",
            "handlers": {},
            "visible": true
        },
        "n1bns18x494nl7q3": {
            "id": "n1bns18x494nl7q3",
            "type": "columns",
            "content": {},
            "isCodeManaged": false,
            "position": 0,
            "parentId": "ccad7k7sc5oxy81l",
            "handlers": {},
            "visible": true
        },
        "ofj7d8hv9f34tr3x": {
            "id": "ofj7d8hv9f34tr3x",
            "type": "column",
            "content": {
                "width": "1"
            },
            "isCodeManaged": false,
            "position": 0,
            "parentId": "n1bns18x494nl7q3",
            "handlers": {},
            "visible": true
        },
        "0h1zk1okn0ouaspi": {
            "id": "0h1zk1okn0ouaspi",
            "type": "selectinput",
            "content": {
                "label": "",
                "options": "@{categories}",
                "placeholder": "Kategori",
                "maximumCount": "1",
                "cssClasses": "",
                "selectedColor": "#FFFFFF",
                "accentColor": "#F3F7F4",
                "chipTextColor": "#136F63",
                "primaryTextColor": "#136F63"
            },
            "isCodeManaged": false,
            "position": 0,
            "parentId": "ofj7d8hv9f34tr3x",
            "handlers": {
                "ss-option-change": "set_category"
            },
            "visible": true,
            "binding": {
                "eventType": "ss-option-change",
                "stateRef": "parameter.category.value"
            }
        },
        "pp2dr6b9nm107lk1": {
            "id": "pp2dr6b9nm107lk1",
            "type": "button",
            "content": {
                "text": "Hent dagens priser for @{parameter.category.name}",
                "separatorColor": "#06070E"
            },
            "isCodeManaged": false,
            "position": 0,
            "parentId": "bsydyjlumqy0kcn1",
            "handlers": {
                "ss-click": "get_products"
            },
            "visible": "flag.fetch_allowed"
        },
        "f2z440vk7btjnj01": {
            "id": "f2z440vk7btjnj01",
            "type": "message",
            "content": {
                "message": "%Fetching",
                "loadingColor": "#136F63"
            },
            "isCodeManaged": false,
            "position": 1,
            "parentId": "ccad7k7sc5oxy81l",
            "handlers": {},
            "visible": "flag.fetching"
        },
        "ep60i50awfyxuux2": {
            "id": "ep60i50awfyxuux2",
            "type": "message",
            "content": {
                "message": "%Updating",
                "loadingColor": "#136F63"
            },
            "isCodeManaged": false,
            "position": 2,
            "parentId": "ccad7k7sc5oxy81l",
            "handlers": {},
            "visible": "flag.updating"
        },
        "56a17g5y715knvqv": {
            "id": "56a17g5y715knvqv",
            "type": "dataframe",
            "content": {
                "dataframe": "@{data}",
                "displayRowCount": "",
                "dataframeBackgroundColor": "#FFFFFF",
                "dataframeHeaderRowBackgroundColor": "#F3F7F4",
                "fontStyle": "monospace"
            },
            "isCodeManaged": false,
            "position": 3,
            "parentId": "ccad7k7sc5oxy81l",
            "handlers": {},
            "visible": true
        },
        "bsydyjlumqy0kcn1": {
            "id": "bsydyjlumqy0kcn1",
            "type": "column",
            "content": {
                "width": "1"
            },
            "isCodeManaged": false,
            "position": 1,
            "parentId": "n1bns18x494nl7q3",
            "handlers": {},
            "visible": true
        }
    }
}